capirca/__init__.py
capirca/aclgen.py
capirca/lib/__init__.py
capirca/lib/aclcheck.py
capirca/lib/aclgenerator.py
capirca/lib/arista.py
capirca/lib/arista_tp.py
capirca/lib/aruba.py
capirca/lib/brocade.py
capirca/lib/cisco.py
capirca/lib/ciscoasa.py
capirca/lib/cisconx.py
capirca/lib/ciscoxr.py
capirca/lib/cloudarmor.py
capirca/lib/demo.py
capirca/lib/gce.py
capirca/lib/gce_vpc_tf.py
capirca/lib/gcp.py
capirca/lib/gcp_hf.py
capirca/lib/ipset.py
capirca/lib/iptables.py
capirca/lib/juniper.py
capirca/lib/juniperevo.py
capirca/lib/junipermsmpc.py
capirca/lib/junipersrx.py
capirca/lib/k8s.py
capirca/lib/nacaddr.py
capirca/lib/naming.py
capirca/lib/nftables.py
capirca/lib/nsxv.py
capirca/lib/openconfig.py
capirca/lib/packetfilter.py
capirca/lib/paloaltofw.py
capirca/lib/pcap.py
capirca/lib/policy.py
capirca/lib/policy_simple.py
capirca/lib/policyreader.py
capirca/lib/port.py
capirca/lib/sonic.py
capirca/lib/speedway.py
capirca/lib/srxlo.py
capirca/lib/summarizer.py
capirca/lib/windows.py
capirca/lib/windows_advfirewall.py
capirca/lib/windows_ipsec.py
capirca/utils/__init__.py
capirca/utils/config.py
capirca/utils/iputils.py
capirca-2.0.9.dist-info/AUTHORS
capirca-2.0.9.dist-info/LICENSE
capirca-2.0.9.dist-info/METADATA
capirca-2.0.9.dist-info/WHEEL
capirca-2.0.9.dist-info/entry_points.txt
capirca-2.0.9.dist-info/top_level.txt
capirca-2.0.9.dist-info/RECORD
