Metadata-Version: 2.1
Name: capirca
Version: 2.0.9
Summary: Capirca
Home-page: https://github.com/google/capirca/
Maintainer: Capirca Team
Maintainer-email: capirca-dev@google.com
License: Apache License, Version 2.0
Classifier: Development Status :: 5 - Production/Stable
Classifier: License :: OSI Approved :: Apache Software License
Classifier: Operating System :: OS Independent
Classifier: Programming Language :: Python :: 3
Classifier: Programming Language :: Python :: 3.6
Classifier: Topic :: Security
Classifier: Topic :: System :: Networking :: Firewalls
Requires-Python: >=3.6
License-File: LICENSE
License-File: AUTHORS
Requires-Dist: absl-py
Requires-Dist: ply
Requires-Dist: mock
Requires-Dist: six
Requires-Dist: PyYAML
